esc_ls/__init__.py
esc_ls/_version.py
esc_ls/plugin.py
esc_ls-0.1.6.dist-info/LICENSE
esc_ls-0.1.6.dist-info/METADATA
esc_ls-0.1.6.dist-info/WHEEL
esc_ls-0.1.6.dist-info/entry_points.txt
esc_ls-0.1.6.dist-info/top_level.txt
esc_ls-0.1.6.dist-info/RECORD
